pkgutil_resolve_name.py
pkgutil_resolve_name-1.0.0.dist-info/LICENSE
pkgutil_resolve_name-1.0.0.dist-info/WHEEL
pkgutil_resolve_name-1.0.0.dist-info/METADATA
pkgutil_resolve_name-1.0.0.dist-info/RECORD
