Metadata-Version: 2.1
Name: pkgutil_resolve_name
Version: 1.0.0
Summary: Resolve a name to an object.
Home-page: https://github.com/graingert/pkgutil-resolve-name
License: UNKNOWN
Author: Vinay Sajip
Author-email: vinay_sajip@yahoo.co.uk
Maintainer: Thomas Grainger
Maintainer-email: pkgutil-resolve-name@graingert.co.uk
Classifier: License :: OSI Approved :: MIT License
